BlueTools/ComplexBlueFile.py
BlueTools/__init__.py
BlueTools-0.1.dist-info/LICENSE
BlueTools-0.1.dist-info/METADATA
BlueTools-0.1.dist-info/WHEEL
BlueTools-0.1.dist-info/top_level.txt
BlueTools-0.1.dist-info/RECORD
