Metadata-Version: 2.1
Name: BlueTools
Version: 0.1
Summary: Tools for working with Blue Files
Home-page: https://github.com/pypa/sampleproject
Author: Example Author
Author-email: the.nostra.tymus@gmail.com
License: UNKNOWN
Project-URL: Bug Tracker, https://github.com/pypa/sampleproject/issues
Platform: UNKNOWN
Classifier: Programming Language :: Python :: 3
Classifier: License :: OSI Approved :: MIT License
Classifier: Operating System :: OS Independent
Requires-Python: >=3.6
